{
    "area": "themes",
    "content_type": "SN|Theme",
    "description": "Elegant utilitarianism.",
    "dock_icon": {
        "background_color": "#086DD6",
        "border_color": "#086DD6",
        "foreground_color": "#ffffff",
        "type": "circle"
    },
    "identifier": "org.standardnotes.theme-midnight",
    "marketing_url": "https://standardnotes.org/extensions/midnight",
    "name": "Midnight",
    "thumbnail_url": "https://s3.amazonaws.com/standard-notes/screenshots/models/themes/midnight-with-mobile.jpg",
    "version": "1.2.1",
    "download_url": "https://api.github.com/repos/standardnotes/midnight-theme/zipball/1.2.1",
    "url": "midnight-theme/dist/dist.css",
    "latest_url": "midnight-theme/index.json"
}