{
    "area": "editor-editor",
    "content_type": "SN|Component",
    "description": "Encrypt and protect your 2FA secrets for all your internet accounts. TokenVault handles your 2FA secrets so that you never lose them again, or have to start over when you get a new device.",
    "flags": [
        "Beta"
    ],
    "identifier": "org.standardnotes.token-vault",
    "name": "TokenVault",
    "thumbnail_url": "https://standard-notes.s3.amazonaws.com/screenshots/models/editors/token-vault.png",
    "version": "1.0.6",
    "download_url": "https://api.github.com/repos/standardnotes/token-vault/zipball/1.0.6",
    "url": "token-vault/dist/index.html",
    "latest_url": "token-vault/index.json"
}